LICENSE
custom_logger/__init__.py
custom_logger/logger.py
python_custom_logger-1.0.4.dist-info/LICENSE
python_custom_logger-1.0.4.dist-info/METADATA
python_custom_logger-1.0.4.dist-info/WHEEL
python_custom_logger-1.0.4.dist-info/RECORD
