Metadata-Version: 2.1
Name: python-custom-logger
Version: 1.0.4
Summary: This package provides a python logger which is simple to use and logs structured logs per default for the gcp.
Home-page: https://github.com/Depaccu/python-custom-logger
License: MIT
Keywords: gcp,logger,structured,logs
Author: JUNGELEN
Author-email: jeffrey_ungelenk@icloud.com
Requires-Python: >=3.11,<4.0
Classifier: License :: OSI Approved :: MIT License
Classifier: Programming Language :: Python :: 3
Classifier: Programming Language :: Python :: 3.11
Classifier: Programming Language :: Python :: 3.12
Requires-Dist: google-cloud-logging (>=3.10.0,<4.0.0)
Project-URL: Repository, https://github.com/Depaccu/python-custom-logger
